{"_id":{"$oid":"675464932c9fb546b03edffb"},"city":"Trento","coordinates":{"lon":11.1211,"lat":46.0679},"weather":{"id":804,"main":"Clouds","description":"overcast clouds","icon":"04d"},"temperature":8.64,"feels_like":8.64,"temp_min":7.17,"temp_max":9.2,"pressure":1009,"humidity":38,"wind":{"speed":0.87,"deg":186,"gust":0.76},"rain":{},"clouds":100,"sunrise":1733553853,"sunset":1733585419,"timestamp":1733583973}
{"_id":{"$oid":"675464942c9fb546b03edffc"},"city":"Rovereto","coordinates":{"lon":11.0387,"lat":45.8896},"weather":{"id":804,"main":"Clouds","description":"overcast clouds","icon":"04d"},"temperature":8.21,"feels_like":8.21,"temp_min":5.71,"temp_max":9.27,"pressure":1009,"humidity":48,"wind":{"speed":0.89,"deg":143,"gust":0.81},"rain":{},"clouds":100,"sunrise":1733553833,"sunset":1733585478,"timestamp":1733583985}
{"_id":{"$oid":"675464952c9fb546b03edffd"},"city":"Pergine Valsugana","coordinates":{"lon":11.238,"lat":46.065},"weather":{"id":804,"main":"Clouds","description":"overcast clouds","icon":"04d"},"temperature":5.98,"feels_like":5.98,"temp_min":3.79,"temp_max":7.35,"pressure":1009,"humidity":42,"wind":{"speed":1.29,"deg":172,"gust":1.12},"rain":{},"clouds":100,"sunrise":1733553824,"sunset":1733585392,"timestamp":1733584021}
{"_id":{"$oid":"675464962c9fb546b03edffe"},"city":"Arco","coordinates":{"lon":10.8867,"lat":45.9177},"weather":{"id":804,"main":"Clouds","description":"overcast clouds","icon":"04d"},"temperature":9.33,"feels_like":9.33,"temp_min":9.26,"temp_max":9.4,"pressure":1009,"humidity":38,"wind":{"speed":0.57,"deg":161,"gust":0.57},"rain":{},"clouds":100,"sunrise":1733553876,"sunset":1733585508,"timestamp":1733584022}
{"_id":{"$oid":"675464972c9fb546b03edfff"},"city":"Riva del Garda","coordinates":{"lon":10.8412,"lat":45.8858},"weather":{"id":804,"main":"Clouds","description":"overcast clouds","icon":"04d"},"temperature":9.43,"feels_like":9.43,"temp_min":9.34,"temp_max":9.48,"pressure":1009,"humidity":65,"wind":{"speed":0.65,"deg":161,"gust":0.67},"rain":{},"clouds":100,"sunrise":1733553880,"sunset":1733585526,"timestamp":1733584023}
{"_id":{"$oid":"675464982c9fb546b03ee000"},"city":"Lavis","coordinates":{"lon":11.1129,"lat":46.1395},"weather":{"id":804,"main":"Clouds","description":"overcast clouds","icon":"04d"},"temperature":6.43,"feels_like":6.43,"temp_min":4.82,"temp_max":8.74,"pressure":1009,"humidity":47,"wind":{"speed":0.45,"deg":336,"gust":1.34},"rain":{},"clouds":100,"sunrise":1733553871,"sunset":1733585405,"timestamp":1733584024}
{"_id":{"$oid":"675464992c9fb546b03ee001"},"city":"Aalen","coordinates":{"lon":10.0933,"lat":48.8378},"weather":{"id":501,"main":"Rain","description":"moderate rain","icon":"10d"},"temperature":4.5,"feels_like":1.72,"temp_min":3.48,"temp_max":6.21,"pressure":1003,"humidity":91,"wind":{"speed":3.25,"deg":186,"gust":8.74},"rain":{"1h":1.13},"clouds":100,"sunrise":1733554755,"sunset":1733585011,"timestamp":1733584025}
{"_id":{"$oid":"6754649a2c9fb546b03ee002"},"city":"Mori","coordinates":{"lon":137.9333,"lat":34.8333},"weather":{"id":804,"main":"Clouds","description":"overcast clouds","icon":"04n"},"temperature":8.02,"feels_like":4.96,"temp_min":8.02,"temp_max":8.02,"pressure":1014,"humidity":59,"wind":{"speed":5.39,"deg":289,"gust":12.61},"rain":{},"clouds":100,"sunrise":1733607809,"sunset":1733643426,"timestamp":1733584026}
{"_id":{"$oid":"6754649c2c9fb546b03ee003"},"city":"Mezzolombardo","coordinates":{"lon":11.0968,"lat":46.209},"weather":{"id":804,"main":"Clouds","description":"overcast clouds","icon":"04d"},"temperature":6.42,"feels_like":6.42,"temp_min":4.87,"temp_max":8.8,"pressure":1009,"humidity":46,"wind":{"speed":0.45,"deg":336,"gust":1.34},"rain":{},"clouds":100,"sunrise":1733553890,"sunset":1733585393,"timestamp":1733584027}
{"_id":{"$oid":"6754649d2c9fb546b03ee004"},"city":"Borgo Valsugana","coordinates":{"lon":11.4544,"lat":46.0514},"weather":{"id":804,"main":"Clouds","description":"overcast clouds","icon":"04d"},"temperature":6.69,"feels_like":6.05,"temp_min":4.34,"temp_max":7.9,"pressure":1009,"humidity":42,"wind":{"speed":1.36,"deg":139,"gust":1.44},"rain":{},"clouds":100,"sunrise":1733553769,"sunset":1733585343,"timestamp":1733584029}
{"_id":{"$oid":"67547b8511da78b55a4d2510"},"city":"Trento","coordinates":{"lon":11.1211,"lat":46.0679},"weather":{"id":800,"main":"Clear","description":"clear sky","icon":"01n"},"temperature":6.3,"feels_like":2.48,"temp_min":3.96,"temp_max":7.61,"pressure":1009,"humidity":44,"wind":{"speed":6.17,"deg":190},"rain":{},"clouds":0,"sunrise":1733553853,"sunset":1733585419,"timestamp":1733589828}
{"_id":{"$oid":"67547b8611da78b55a4d2511"},"city":"Rovereto","coordinates":{"lon":11.0387,"lat":45.8896},"weather":{"id":804,"main":"Clouds","description":"overcast clouds","icon":"04n"},"temperature":4.89,"feels_like":3.74,"temp_min":3.49,"temp_max":7.6,"pressure":1008,"humidity":56,"wind":{"speed":1.56,"deg":69,"gust":1.41},"rain":{},"clouds":100,"sunrise":1733553833,"sunset":1733585478,"timestamp":1733589600}
{"_id":{"$oid":"67547b8711da78b55a4d2512"},"city":"Pergine Valsugana","coordinates":{"lon":11.238,"lat":46.065},"weather":{"id":800,"main":"Clear","description":"clear sky","icon":"01n"},"temperature":3.36,"feels_like":-1.26,"temp_min":1.57,"temp_max":5.77,"pressure":1009,"humidity":52,"wind":{"speed":6.17,"deg":190},"rain":{},"clouds":0,"sunrise":1733553824,"sunset":1733585392,"timestamp":1733589674}
{"_id":{"$oid":"67547b8811da78b55a4d2513"},"city":"Arco","coordinates":{"lon":10.8867,"lat":45.9177},"weather":{"id":804,"main":"Clouds","description":"overcast clouds","icon":"04n"},"temperature":6.96,"feels_like":5.95,"temp_min":5.53,"temp_max":8.29,"pressure":1008,"humidity":68,"wind":{"speed":1.7,"deg":30,"gust":1.67},"rain":{},"clouds":100,"sunrise":1733553876,"sunset":1733585508,"timestamp":1733589896}
{"_id":{"$oid":"67547b8a11da78b55a4d2514"},"city":"Riva del Garda","coordinates":{"lon":10.8412,"lat":45.8858},"weather":{"id":804,"main":"Clouds","description":"overcast clouds","icon":"04n"},"temperature":5.61,"feels_like":3.97,"temp_min":5.61,"temp_max":8.37,"pressure":1008,"humidity":57,"wind":{"speed":2.11,"deg":31,"gust":2.19},"rain":{},"clouds":100,"sunrise":1733553880,"sunset":1733585526,"timestamp":1733589898}
{"_id":{"$oid":"67547b8b11da78b55a4d2515"},"city":"Lavis","coordinates":{"lon":11.1129,"lat":46.1395},"weather":{"id":800,"main":"Clear","description":"clear sky","icon":"01n"},"temperature":4.91,"feels_like":0.71,"temp_min":3.16,"temp_max":7.36,"pressure":1009,"humidity":48,"wind":{"speed":6.17,"deg":190},"rain":{},"clouds":0,"sunrise":1733553871,"sunset":1733585405,"timestamp":1733589899}
{"_id":{"$oid":"67547b8c11da78b55a4d2516"},"city":"Aalen","coordinates":{"lon":10.0933,"lat":48.8378},"weather":{"id":500,"main":"Rain","description":"light rain","icon":"10n"},"temperature":5.27,"feels_like":2.31,"temp_min":4.59,"temp_max":5.98,"pressure":1003,"humidity":92,"wind":{"speed":3.79,"deg":251,"gust":9.47},"rain":{"1h":0.36},"clouds":100,"sunrise":1733554755,"sunset":1733585011,"timestamp":1733589828}
{"_id":{"$oid":"67547b8d11da78b55a4d2517"},"city":"Mori","coordinates":{"lon":137.9333,"lat":34.8333},"weather":{"id":804,"main":"Clouds","description":"overcast clouds","icon":"04n"},"temperature":8.02,"feels_like":4.91,"temp_min":8.02,"temp_max":8.02,"pressure":1014,"humidity":56,"wind":{"speed":5.5,"deg":289,"gust":13.84},"rain":{},"clouds":100,"sunrise":1733607809,"sunset":1733643426,"timestamp":1733589901}
{"_id":{"$oid":"67547b8e11da78b55a4d2518"},"city":"Mezzolombardo","coordinates":{"lon":11.0968,"lat":46.209},"weather":{"id":800,"main":"Clear","description":"clear sky","icon":"01n"},"temperature":5.18,"feels_like":1.06,"temp_min":3.22,"temp_max":6.89,"pressure":1009,"humidity":46,"wind":{"speed":6.17,"deg":190},"rain":{},"clouds":0,"sunrise":1733553890,"sunset":1733585393,"timestamp":1733589902}
{"_id":{"$oid":"67547b8f11da78b55a4d2519"},"city":"Borgo Valsugana","coordinates":{"lon":11.4544,"lat":46.0514},"weather":{"id":804,"main":"Clouds","description":"overcast clouds","icon":"04n"},"temperature":4.04,"feels_like":2.87,"temp_min":2.12,"temp_max":5.76,"pressure":1009,"humidity":51,"wind":{"speed":1.49,"deg":90,"gust":1.43},"rain":{},"clouds":100,"sunrise":1733553769,"sunset":1733585343,"timestamp":1733589903}
{"_id":{"$oid":"67547ef941152ccf9030a61a"},"city":"Trento","coordinates":{"lon":11.1211,"lat":46.0679},"weather":{"id":800,"main":"Clear","description":"clear sky","icon":"01n"},"temperature":5.34,"feels_like":1.26,"temp_min":3.28,"temp_max":7.61,"pressure":1009,"humidity":52,"wind":{"speed":6.17,"deg":190},"rain":{},"clouds":0,"sunrise":1733553853,"sunset":1733585419,"timestamp":1733590654}
{"_id":{"$oid":"67547efb41152ccf9030a61b"},"city":"Rovereto","coordinates":{"lon":11.0387,"lat":45.8896},"weather":{"id":804,"main":"Clouds","description":"overcast clouds","icon":"04n"},"temperature":4.31,"feels_like":3.08,"temp_min":3.36,"temp_max":7.16,"pressure":1008,"humidity":60,"wind":{"speed":1.56,"deg":69,"gust":1.41},"rain":{},"clouds":100,"sunrise":1733553833,"sunset":1733585478,"timestamp":1733590779}
{"_id":{"$oid":"67547efc41152ccf9030a61c"},"city":"Pergine Valsugana","coordinates":{"lon":11.238,"lat":46.065},"weather":{"id":800,"main":"Clear","description":"clear sky","icon":"01n"},"temperature":3.2,"feels_like":-3.8,"temp_min":1.44,"temp_max":5.24,"pressure":1009,"humidity":52,"wind":{"speed":22.35,"deg":0,"gust":22.35},"rain":{},"clouds":0,"sunrise":1733553824,"sunset":1733585392,"timestamp":1733590780}
{"_id":{"$oid":"67547efd41152ccf9030a61d"},"city":"Arco","coordinates":{"lon":10.8867,"lat":45.9177},"weather":{"id":804,"main":"Clouds","description":"overcast clouds","icon":"04n"},"temperature":6.96,"feels_like":5.95,"temp_min":5.53,"temp_max":8.29,"pressure":1008,"humidity":68,"wind":{"speed":1.7,"deg":30,"gust":1.67},"rain":{},"clouds":100,"sunrise":1733553876,"sunset":1733585508,"timestamp":1733590723}
{"_id":{"$oid":"67547efe41152ccf9030a61e"},"city":"Riva del Garda","coordinates":{"lon":10.8412,"lat":45.8858},"weather":{"id":804,"main":"Clouds","description":"overcast clouds","icon":"04n"},"temperature":5.61,"feels_like":3.97,"temp_min":5.61,"temp_max":8.37,"pressure":1008,"humidity":60,"wind":{"speed":2.11,"deg":31,"gust":2.19},"rain":{},"clouds":100,"sunrise":1733553880,"sunset":1733585526,"timestamp":1733590702}
{"_id":{"$oid":"67547eff41152ccf9030a61f"},"city":"Lavis","coordinates":{"lon":11.1129,"lat":46.1395},"weather":{"id":800,"main":"Clear","description":"clear sky","icon":"01n"},"temperature":4.99,"feels_like":0.81,"temp_min":3.16,"temp_max":7.36,"pressure":1009,"humidity":48,"wind":{"speed":6.17,"deg":190},"rain":{},"clouds":0,"sunrise":1733553871,"sunset":1733585405,"timestamp":1733590783}
{"_id":{"$oid":"67547f0041152ccf9030a620"},"city":"Aalen","coordinates":{"lon":10.0933,"lat":48.8378},"weather":{"id":501,"main":"Rain","description":"moderate rain","icon":"10n"},"temperature":5.08,"feels_like":2.08,"temp_min":4.59,"temp_max":7.32,"pressure":1003,"humidity":92,"wind":{"speed":3.79,"deg":251,"gust":9.47},"rain":{"1h":2.73},"clouds":100,"sunrise":1733554755,"sunset":1733585011,"timestamp":1733590784}
{"_id":{"$oid":"67547f0141152ccf9030a621"},"city":"Mori","coordinates":{"lon":137.9333,"lat":34.8333},"weather":{"id":804,"main":"Clouds","description":"overcast clouds","icon":"04n"},"temperature":8.02,"feels_like":4.91,"temp_min":8.02,"temp_max":8.02,"pressure":1014,"humidity":54,"wind":{"speed":5.5,"deg":289,"gust":13.84},"rain":{},"clouds":100,"sunrise":1733607809,"sunset":1733643426,"timestamp":1733590785}
{"_id":{"$oid":"67547f0241152ccf9030a622"},"city":"Mezzolombardo","coordinates":{"lon":11.0968,"lat":46.209},"weather":{"id":800,"main":"Clear","description":"clear sky","icon":"01n"},"temperature":5.28,"feels_like":1.18,"temp_min":3.21,"temp_max":6.89,"pressure":1009,"humidity":46,"wind":{"speed":6.17,"deg":190},"rain":{},"clouds":0,"sunrise":1733553890,"sunset":1733585393,"timestamp":1733590786}
{"_id":{"$oid":"67547f0341152ccf9030a623"},"city":"Borgo Valsugana","coordinates":{"lon":11.4544,"lat":46.0514},"weather":{"id":804,"main":"Clouds","description":"overcast clouds","icon":"04n"},"temperature":4.35,"feels_like":-2.65,"temp_min":1.99,"temp_max":5.76,"pressure":1009,"humidity":51,"wind":{"speed":22.35,"deg":0,"gust":22.35},"rain":{},"clouds":100,"sunrise":1733553769,"sunset":1733585343,"timestamp":1733590787}
{"_id":{"$oid":"675481a9a6faa065fdb56952"},"city":"Trento","coordinates":{"lon":11.1211,"lat":46.0679},"weather":{"id":804,"main":"Clouds","description":"overcast clouds","icon":"04n"},"temperature":4.32,"feels_like":4.32,"temp_min":3.07,"temp_max":7.06,"pressure":1009,"humidity":57,"wind":{"speed":0.45,"deg":32,"gust":0.89},"rain":{},"clouds":100,"sunrise":1733553853,"sunset":1733585419,"timestamp":1733591294}
{"_id":{"$oid":"675481aba6faa065fdb56953"},"city":"Rovereto","coordinates":{"lon":11.0387,"lat":45.8896},"weather":{"id":804,"main":"Clouds","description":"overcast clouds","icon":"04n"},"temperature":4.35,"feels_like":3.13,"temp_min":3.14,"temp_max":7.13,"pressure":1008,"humidity":59,"wind":{"speed":1.56,"deg":69,"gust":1.41},"rain":{},"clouds":100,"sunrise":1733553833,"sunset":1733585478,"timestamp":1733591184}
{"_id":{"$oid":"675481aca6faa065fdb56954"},"city":"Pergine Valsugana","coordinates":{"lon":11.238,"lat":46.065},"weather":{"id":804,"main":"Clouds","description":"overcast clouds","icon":"04n"},"temperature":2.96,"feels_like":1.25,"temp_min":1.22,"temp_max":5.22,"pressure":1009,"humidity":55,"wind":{"speed":1.78,"deg":114,"gust":1.48},"rain":{},"clouds":100,"sunrise":1733553824,"sunset":1733585392,"timestamp":1733591468}
{"_id":{"$oid":"675481ada6faa065fdb56955"},"city":"Arco","coordinates":{"lon":10.8867,"lat":45.9177},"weather":{"id":804,"main":"Clouds","description":"overcast clouds","icon":"04n"},"temperature":5.53,"feels_like":4.31,"temp_min":5.53,"temp_max":5.53,"pressure":1008,"humidity":68,"wind":{"speed":1.7,"deg":30,"gust":1.67},"rain":{},"clouds":100,"sunrise":1733553876,"sunset":1733585508,"timestamp":1733591236}
{"_id":{"$oid":"675481aea6faa065fdb56956"},"city":"Riva del Garda","coordinates":{"lon":10.8412,"lat":45.8858},"weather":{"id":804,"main":"Clouds","description":"overcast clouds","icon":"04n"},"temperature":5.61,"feels_like":3.97,"temp_min":5.61,"temp_max":5.61,"pressure":1008,"humidity":59,"wind":{"speed":2.11,"deg":31,"gust":2.19},"rain":{},"clouds":100,"sunrise":1733553880,"sunset":1733585526,"timestamp":1733591470}
{"_id":{"$oid":"675481afa6faa065fdb56957"},"city":"Lavis","coordinates":{"lon":11.1129,"lat":46.1395},"weather":{"id":804,"main":"Clouds","description":"overcast clouds","icon":"04n"},"temperature":3.46,"feels_like":3.46,"temp_min":2.81,"temp_max":5.96,"pressure":1009,"humidity":57,"wind":{"speed":0.45,"deg":32,"gust":0.89},"rain":{},"clouds":100,"sunrise":1733553871,"sunset":1733585405,"timestamp":1733591229}
{"_id":{"$oid":"675481b0a6faa065fdb56958"},"city":"Aalen","coordinates":{"lon":10.0933,"lat":48.8378},"weather":{"id":501,"main":"Rain","description":"moderate rain","icon":"10n"},"temperature":5.07,"feels_like":2.07,"temp_min":4.59,"temp_max":5.98,"pressure":1003,"humidity":92,"wind":{"speed":3.79,"deg":251,"gust":9.47},"rain":{"1h":1.82},"clouds":100,"sunrise":1733554755,"sunset":1733585011,"timestamp":1733591200}
{"_id":{"$oid":"675481b1a6faa065fdb56959"},"city":"Mori","coordinates":{"lon":137.9333,"lat":34.8333},"weather":{"id":804,"main":"Clouds","description":"overcast clouds","icon":"04n"},"temperature":8.02,"feels_like":4.91,"temp_min":8.02,"temp_max":8.02,"pressure":1014,"humidity":53,"wind":{"speed":5.5,"deg":289,"gust":13.84},"rain":{},"clouds":100,"sunrise":1733607809,"sunset":1733643426,"timestamp":1733591473}
{"_id":{"$oid":"675481b2a6faa065fdb5695a"},"city":"Mezzolombardo","coordinates":{"lon":11.0968,"lat":46.209},"weather":{"id":804,"main":"Clouds","description":"overcast clouds","icon":"04n"},"temperature":3.77,"feels_like":3.77,"temp_min":2.87,"temp_max":6.02,"pressure":1009,"humidity":54,"wind":{"speed":0.45,"deg":32,"gust":0.89},"rain":{},"clouds":100,"sunrise":1733553890,"sunset":1733585393,"timestamp":1733591474}
{"_id":{"$oid":"675481b3a6faa065fdb5695b"},"city":"Borgo Valsugana","coordinates":{"lon":11.4544,"lat":46.0514},"weather":{"id":804,"main":"Clouds","description":"overcast clouds","icon":"04n"},"temperature":4.36,"feels_like":3.23,"temp_min":1.77,"temp_max":5.76,"pressure":1009,"humidity":52,"wind":{"speed":1.49,"deg":90,"gust":1.43},"rain":{},"clouds":100,"sunrise":1733553769,"sunset":1733585343,"timestamp":1733591475}
{"_id":{"$oid":"675483ab9e5596b77c188a54"},"city":"Trento","coordinates":{"lon":11.1211,"lat":46.0679},"weather":{"id":804,"main":"Clouds","description":"overcast clouds","icon":"04n"},"temperature":4.32,"feels_like":4.32,"temp_min":3.07,"temp_max":7.06,"pressure":1009,"humidity":57,"wind":{"speed":0.45,"deg":32,"gust":0.89},"rain":{},"clouds":100,"sunrise":1733553853,"sunset":1733585419,"timestamp":1733591807}
{"_id":{"$oid":"675483ac9e5596b77c188a55"},"city":"Rovereto","coordinates":{"lon":11.0387,"lat":45.8896},"weather":{"id":804,"main":"Clouds","description":"overcast clouds","icon":"04n"},"temperature":4.24,"feels_like":3,"temp_min":2.44,"temp_max":7.05,"pressure":1008,"humidity":59,"wind":{"speed":1.56,"deg":69,"gust":1.41},"rain":{},"clouds":100,"sunrise":1733553833,"sunset":1733585478,"timestamp":1733591920}
{"_id":{"$oid":"675483ae9e5596b77c188a56"},"city":"Pergine Valsugana","coordinates":{"lon":11.238,"lat":46.065},"weather":{"id":801,"main":"Clouds","description":"few clouds","icon":"02n"},"temperature":2.77,"feels_like":-2.01,"temp_min":0.88,"temp_max":5.13,"pressure":1009,"humidity":54,"wind":{"speed":6.17,"deg":180},"rain":{},"clouds":20,"sunrise":1733553824,"sunset":1733585392,"timestamp":1733591982}
{"_id":{"$oid":"675483af9e5596b77c188a57"},"city":"Arco","coordinates":{"lon":10.8867,"lat":45.9177},"weather":{"id":804,"main":"Clouds","description":"overcast clouds","icon":"04n"},"temperature":5.53,"feels_like":4.31,"temp_min":5.53,"temp_max":6.77,"pressure":1008,"humidity":68,"wind":{"speed":1.7,"deg":30,"gust":1.67},"rain":{},"clouds":100,"sunrise":1733553876,"sunset":1733585508,"timestamp":1733591983}
{"_id":{"$oid":"675483b09e5596b77c188a58"},"city":"Riva del Garda","coordinates":{"lon":10.8412,"lat":45.8858},"weather":{"id":804,"main":"Clouds","description":"overcast clouds","icon":"04n"},"temperature":5.61,"feels_like":3.97,"temp_min":5.61,"temp_max":5.61,"pressure":1008,"humidity":59,"wind":{"speed":2.11,"deg":31,"gust":2.19},"rain":{},"clouds":100,"sunrise":1733553880,"sunset":1733585526,"timestamp":1733591703}
{"_id":{"$oid":"675483b19e5596b77c188a59"},"city":"Lavis","coordinates":{"lon":11.1129,"lat":46.1395},"weather":{"id":804,"main":"Clouds","description":"overcast clouds","icon":"04n"},"temperature":3.46,"feels_like":3.46,"temp_min":2.81,"temp_max":5.96,"pressure":1009,"humidity":57,"wind":{"speed":0.45,"deg":32,"gust":0.89},"rain":{},"clouds":100,"sunrise":1733553871,"sunset":1733585405,"timestamp":1733591700}
{"_id":{"$oid":"675483b29e5596b77c188a5a"},"city":"Aalen","coordinates":{"lon":10.0933,"lat":48.8378},"weather":{"id":500,"main":"Rain","description":"light rain","icon":"10n"},"temperature":4.97,"feels_like":1.95,"temp_min":4.03,"temp_max":5.98,"pressure":1003,"humidity":92,"wind":{"speed":3.79,"deg":251,"gust":9.47},"rain":{"1h":0.23},"clouds":100,"sunrise":1733554755,"sunset":1733585011,"timestamp":1733591906}
{"_id":{"$oid":"675483b39e5596b77c188a5b"},"city":"Mori","coordinates":{"lon":137.9333,"lat":34.8333},"weather":{"id":804,"main":"Clouds","description":"overcast clouds","icon":"04n"},"temperature":8.02,"feels_like":4.91,"temp_min":8.02,"temp_max":8.02,"pressure":1014,"humidity":53,"wind":{"speed":5.5,"deg":289,"gust":13.84},"rain":{},"clouds":100,"sunrise":1733607809,"sunset":1733643426,"timestamp":1733591987}
{"_id":{"$oid":"675483b49e5596b77c188a5c"},"city":"Mezzolombardo","coordinates":{"lon":11.0968,"lat":46.209},"weather":{"id":801,"main":"Clouds","description":"few clouds","icon":"02n"},"temperature":4.46,"feels_like":0.14,"temp_min":2.87,"temp_max":6.31,"pressure":1009,"humidity":49,"wind":{"speed":6.17,"deg":180},"rain":{},"clouds":20,"sunrise":1733553890,"sunset":1733585393,"timestamp":1733591988}
{"_id":{"$oid":"675483b59e5596b77c188a5d"},"city":"Borgo Valsugana","coordinates":{"lon":11.4544,"lat":46.0514},"weather":{"id":804,"main":"Clouds","description":"overcast clouds","icon":"04n"},"temperature":4.22,"feels_like":3.07,"temp_min":1.77,"temp_max":5.7,"pressure":1009,"humidity":52,"wind":{"speed":1.49,"deg":90,"gust":1.43},"rain":{},"clouds":100,"sunrise":1733553769,"sunset":1733585343,"timestamp":1733591989}
{"_id":{"$oid":"675487b0b8b4b127c65363fd"},"city":"Trento","coordinates":{"lon":11.1211,"lat":46.0679},"weather":{"id":801,"main":"Clouds","description":"few clouds","icon":"02n"},"temperature":4.37,"feels_like":0.03,"temp_min":2.72,"temp_max":6.98,"pressure":1008,"humidity":54,"wind":{"speed":6.17,"deg":180},"rain":{},"clouds":20,"sunrise":1733553853,"sunset":1733585419,"timestamp":1733592998}
{"_id":{"$oid":"675487b1b8b4b127c65363fe"},"city":"Rovereto","coordinates":{"lon":11.0387,"lat":45.8896},"weather":{"id":804,"main":"Clouds","description":"overcast clouds","icon":"04n"},"temperature":4.21,"feels_like":2.56,"temp_min":2.8,"temp_max":7.05,"pressure":1007,"humidity":58,"wind":{"speed":1.9,"deg":65,"gust":1.79},"rain":{},"clouds":100,"sunrise":1733553833,"sunset":1733585478,"timestamp":1733592936}
{"_id":{"$oid":"675487b2b8b4b127c65363ff"},"city":"Pergine Valsugana","coordinates":{"lon":11.238,"lat":46.065},"weather":{"id":801,"main":"Clouds","description":"few clouds","icon":"02n"},"temperature":2.55,"feels_like":-3.99,"temp_min":0.88,"temp_max":5.13,"pressure":1007,"humidity":54,"wind":{"speed":11.18,"deg":0,"gust":38.89},"rain":{},"clouds":20,"sunrise":1733553824,"sunset":1733585392,"timestamp":1733593010}
{"_id":{"$oid":"675487b3b8b4b127c6536400"},"city":"Arco","coordinates":{"lon":10.8867,"lat":45.9177},"weather":{"id":804,"main":"Clouds","description":"overcast clouds","icon":"04n"},"temperature":5.53,"feels_like":3.77,"temp_min":5.53,"temp_max":6.77,"pressure":1007,"humidity":65,"wind":{"speed":2.22,"deg":38,"gust":2.48},"rain":{},"clouds":100,"sunrise":1733553876,"sunset":1733585508,"timestamp":1733592963}
{"_id":{"$oid":"675487b4b8b4b127c6536401"},"city":"Riva del Garda","coordinates":{"lon":10.8412,"lat":45.8858},"weather":{"id":804,"main":"Clouds","description":"overcast clouds","icon":"04n"},"temperature":5.61,"feels_like":3.67,"temp_min":5.61,"temp_max":5.61,"pressure":1007,"humidity":56,"wind":{"speed":2.44,"deg":37,"gust":2.81},"rain":{},"clouds":100,"sunrise":1733553880,"sunset":1733585526,"timestamp":1733593012}
{"_id":{"$oid":"675487b5b8b4b127c6536402"},"city":"Lavis","coordinates":{"lon":11.1129,"lat":46.1395},"weather":{"id":801,"main":"Clouds","description":"few clouds","icon":"02n"},"temperature":4.04,"feels_like":-0.39,"temp_min":2.6,"temp_max":5.83,"pressure":1008,"humidity":51,"wind":{"speed":6.17,"deg":180},"rain":{},"clouds":20,"sunrise":1733553871,"sunset":1733585405,"timestamp":1733593013}
{"_id":{"$oid":"675487b6b8b4b127c6536403"},"city":"Aalen","coordinates":{"lon":10.0933,"lat":48.8378},"weather":{"id":804,"main":"Clouds","description":"overcast clouds","icon":"04n"},"temperature":5.17,"feels_like":1.88,"temp_min":4.71,"temp_max":5.98,"pressure":1003,"humidity":91,"wind":{"speed":4.35,"deg":245,"gust":10.08},"rain":{},"clouds":100,"sunrise":1733554755,"sunset":1733585011,"timestamp":1733592983}
{"_id":{"$oid":"675487b7b8b4b127c6536404"},"city":"Mori","coordinates":{"lon":137.9333,"lat":34.8333},"weather":{"id":804,"main":"Clouds","description":"overcast clouds","icon":"04n"},"temperature":8.02,"feels_like":5.12,"temp_min":8.02,"temp_max":8.02,"pressure":1014,"humidity":54,"wind":{"speed":4.98,"deg":292,"gust":12.78},"rain":{},"clouds":100,"sunrise":1733607809,"sunset":1733643426,"timestamp":1733593015}
{"_id":{"$oid":"675487b8b8b4b127c6536405"},"city":"Mezzolombardo","coordinates":{"lon":11.0968,"lat":46.209},"weather":{"id":801,"main":"Clouds","description":"few clouds","icon":"02n"},"temperature":4.36,"feels_like":0.01,"temp_min":2.66,"temp_max":5.89,"pressure":1008,"humidity":49,"wind":{"speed":6.17,"deg":180},"rain":{},"clouds":20,"sunrise":1733553890,"sunset":1733585393,"timestamp":1733593016}
{"_id":{"$oid":"675487b9b8b4b127c6536406"},"city":"Borgo Valsugana","coordinates":{"lon":11.4544,"lat":46.0514},"weather":{"id":804,"main":"Clouds","description":"overcast clouds","icon":"04n"},"temperature":3.99,"feels_like":-2.06,"temp_min":1.43,"temp_max":5.7,"pressure":1008,"humidity":52,"wind":{"speed":11.18,"deg":0,"gust":38.89},"rain":{},"clouds":100,"sunrise":1733553769,"sunset":1733585343,"timestamp":1733593017}
{"_id":{"$oid":"6754893b1651cdd135489724"},"city":"Trento","coordinates":{"lon":11.1211,"lat":46.0679},"weather":{"id":801,"main":"Clouds","description":"few clouds","icon":"02n"},"temperature":4.28,"feels_like":-0.09,"temp_min":2.72,"temp_max":6.98,"pressure":1008,"humidity":54,"wind":{"speed":6.17,"deg":180},"rain":{},"clouds":20,"sunrise":1733553853,"sunset":1733585419,"timestamp":1733593403}
{"_id":{"$oid":"6754893d1651cdd135489725"},"city":"Rovereto","coordinates":{"lon":11.0387,"lat":45.8896},"weather":{"id":804,"main":"Clouds","description":"overcast clouds","icon":"04n"},"temperature":4.33,"feels_like":2.21,"temp_min":2.8,"temp_max":7.05,"pressure":1007,"humidity":58,"wind":{"speed":2.39,"deg":57,"gust":2.92},"rain":{},"clouds":100,"sunrise":1733553833,"sunset":1733585478,"timestamp":1733593353}
{"_id":{"$oid":"6754893e1651cdd135489726"},"city":"Pergine Valsugana","coordinates":{"lon":11.238,"lat":46.065},"weather":{"id":801,"main":"Clouds","description":"few clouds","icon":"02n"},"temperature":2.88,"feels_like":-1.87,"temp_min":0.88,"temp_max":5.13,"pressure":1008,"humidity":50,"wind":{"speed":6.17,"deg":180},"rain":{},"clouds":20,"sunrise":1733553824,"sunset":1733585392,"timestamp":1733593406}
{"_id":{"$oid":"6754893f1651cdd135489727"},"city":"Arco","coordinates":{"lon":10.8867,"lat":45.9177},"weather":{"id":804,"main":"Clouds","description":"overcast clouds","icon":"04n"},"temperature":6.09,"feels_like":3.82,"temp_min":6.09,"temp_max":6.77,"pressure":1007,"humidity":64,"wind":{"speed":3,"deg":33,"gust":4.13},"rain":{},"clouds":100,"sunrise":1733553876,"sunset":1733585508,"timestamp":1733593407}
{"_id":{"$oid":"675489401651cdd135489728"},"city":"Riva del Garda","coordinates":{"lon":10.8412,"lat":45.8858},"weather":{"id":804,"main":"Clouds","description":"overcast clouds","icon":"04n"},"temperature":6.17,"feels_like":3.69,"temp_min":6.17,"temp_max":6.17,"pressure":1007,"humidity":56,"wind":{"speed":3.34,"deg":33,"gust":4.59},"rain":{},"clouds":100,"sunrise":1733553880,"sunset":1733585526,"timestamp":1733593336}
{"_id":{"$oid":"675489411651cdd135489729"},"city":"Lavis","coordinates":{"lon":11.1129,"lat":46.1395},"weather":{"id":801,"main":"Clouds","description":"few clouds","icon":"02n"},"temperature":4.04,"feels_like":-0.39,"temp_min":2.05,"temp_max":5.83,"pressure":1008,"humidity":52,"wind":{"speed":6.17,"deg":180},"rain":{},"clouds":20,"sunrise":1733553871,"sunset":1733585405,"timestamp":1733593409}
{"_id":{"$oid":"675489421651cdd13548972a"},"city":"Aalen","coordinates":{"lon":10.0933,"lat":48.8378},"weather":{"id":804,"main":"Clouds","description":"overcast clouds","icon":"04n"},"temperature":5.17,"feels_like":1.88,"temp_min":4.71,"temp_max":5.98,"pressure":1003,"humidity":91,"wind":{"speed":4.35,"deg":245,"gust":10.08},"rain":{},"clouds":100,"sunrise":1733554755,"sunset":1733585011,"timestamp":1733593111}
{"_id":{"$oid":"675489431651cdd13548972b"},"city":"Mori","coordinates":{"lon":137.9333,"lat":34.8333},"weather":{"id":500,"main":"Rain","description":"light rain","icon":"10n"},"temperature":8.02,"feels_like":5.12,"temp_min":8.02,"temp_max":8.02,"pressure":1014,"humidity":54,"wind":{"speed":4.98,"deg":292,"gust":12.78},"rain":{"1h":0.11},"clouds":100,"sunrise":1733607809,"sunset":1733643426,"timestamp":1733593411}
{"_id":{"$oid":"675489441651cdd13548972c"},"city":"Mezzolombardo","coordinates":{"lon":11.0968,"lat":46.209},"weather":{"id":801,"main":"Clouds","description":"few clouds","icon":"02n"},"temperature":4.35,"feels_like":0,"temp_min":2.1,"temp_max":5.89,"pressure":1008,"humidity":49,"wind":{"speed":6.17,"deg":180},"rain":{},"clouds":20,"sunrise":1733553890,"sunset":1733585393,"timestamp":1733593412}
{"_id":{"$oid":"675489451651cdd13548972d"},"city":"Borgo Valsugana","coordinates":{"lon":11.4544,"lat":46.0514},"weather":{"id":804,"main":"Clouds","description":"overcast clouds","icon":"04n"},"temperature":4.36,"feels_like":2.64,"temp_min":1.43,"temp_max":5.7,"pressure":1008,"humidity":49,"wind":{"speed":1.98,"deg":67,"gust":1.79},"rain":{},"clouds":100,"sunrise":1733553769,"sunset":1733585343,"timestamp":1733593413}
{"_id":{"$oid":"67548a3fa323e3c4f11e617f"},"city":"Trento","coordinates":{"lon":11.1211,"lat":46.0679},"weather":{"id":801,"main":"Clouds","description":"few clouds","icon":"02n"},"temperature":4.37,"feels_like":0.03,"temp_min":2.72,"temp_max":6.98,"pressure":1008,"humidity":54,"wind":{"speed":6.17,"deg":180},"rain":{},"clouds":20,"sunrise":1733553853,"sunset":1733585419,"timestamp":1733592998}
{"_id":{"$oid":"67548a41a323e3c4f11e6180"},"city":"Rovereto","coordinates":{"lon":11.0387,"lat":45.8896},"weather":{"id":804,"main":"Clouds","description":"overcast clouds","icon":"04n"},"temperature":4.88,"feels_like":2.85,"temp_min":2.93,"temp_max":7.05,"pressure":1007,"humidity":58,"wind":{"speed":2.39,"deg":57,"gust":2.92},"rain":{},"clouds":100,"sunrise":1733553833,"sunset":1733585478,"timestamp":1733593559}
{"_id":{"$oid":"67548a42a323e3c4f11e6181"},"city":"Pergine Valsugana","coordinates":{"lon":11.238,"lat":46.065},"weather":{"id":801,"main":"Clouds","description":"few clouds","icon":"02n"},"temperature":2.87,"feels_like":-4.13,"temp_min":1.01,"temp_max":5.13,"pressure":1008,"humidity":51,"wind":{"speed":16.09,"deg":0,"gust":16.09},"rain":{},"clouds":20,"sunrise":1733553824,"sunset":1733585392,"timestamp":1733593666}
{"_id":{"$oid":"67548a43a323e3c4f11e6182"},"city":"Arco","coordinates":{"lon":10.8867,"lat":45.9177},"weather":{"id":804,"main":"Clouds","description":"overcast clouds","icon":"04n"},"temperature":6.09,"feels_like":3.82,"temp_min":6.09,"temp_max":6.77,"pressure":1007,"humidity":64,"wind":{"speed":3,"deg":33,"gust":4.13},"rain":{},"clouds":100,"sunrise":1733553876,"sunset":1733585508,"timestamp":1733593407}
{"_id":{"$oid":"67548a44a323e3c4f11e6183"},"city":"Riva del Garda","coordinates":{"lon":10.8412,"lat":45.8858},"weather":{"id":804,"main":"Clouds","description":"overcast clouds","icon":"04n"},"temperature":6.17,"feels_like":3.69,"temp_min":6.17,"temp_max":6.17,"pressure":1007,"humidity":58,"wind":{"speed":3.34,"deg":33,"gust":4.59},"rain":{},"clouds":100,"sunrise":1733553880,"sunset":1733585526,"timestamp":1733593668}
{"_id":{"$oid":"67548a45a323e3c4f11e6184"},"city":"Lavis","coordinates":{"lon":11.1129,"lat":46.1395},"weather":{"id":801,"main":"Clouds","description":"few clouds","icon":"02n"},"temperature":4.04,"feels_like":-0.39,"temp_min":2.05,"temp_max":5.83,"pressure":1008,"humidity":52,"wind":{"speed":6.17,"deg":180},"rain":{},"clouds":20,"sunrise":1733553871,"sunset":1733585405,"timestamp":1733593409}
{"_id":{"$oid":"67548a46a323e3c4f11e6185"},"city":"Aalen","coordinates":{"lon":10.0933,"lat":48.8378},"weather":{"id":804,"main":"Clouds","description":"overcast clouds","icon":"04n"},"temperature":4.97,"feels_like":1.49,"temp_min":4.03,"temp_max":5.98,"pressure":1003,"humidity":92,"wind":{"speed":4.61,"deg":237,"gust":10.61},"rain":{},"clouds":100,"sunrise":1733554755,"sunset":1733585011,"timestamp":1733593584}
{"_id":{"$oid":"67548a47a323e3c4f11e6186"},"city":"Mori","coordinates":{"lon":137.9333,"lat":34.8333},"weather":{"id":500,"main":"Rain","description":"light rain","icon":"10n"},"temperature":8.02,"feels_like":5.12,"temp_min":8.02,"temp_max":8.02,"pressure":1014,"humidity":54,"wind":{"speed":4.98,"deg":292,"gust":12.78},"rain":{"1h":0.11},"clouds":100,"sunrise":1733607809,"sunset":1733643426,"timestamp":1733593411}
{"_id":{"$oid":"67548a48a323e3c4f11e6187"},"city":"Mezzolombardo","coordinates":{"lon":11.0968,"lat":46.209},"weather":{"id":801,"main":"Clouds","description":"few clouds","icon":"02n"},"temperature":4.35,"feels_like":0,"temp_min":2.1,"temp_max":5.89,"pressure":1008,"humidity":49,"wind":{"speed":6.17,"deg":180},"rain":{},"clouds":20,"sunrise":1733553890,"sunset":1733585393,"timestamp":1733593672}
{"_id":{"$oid":"67548a49a323e3c4f11e6188"},"city":"Borgo Valsugana","coordinates":{"lon":11.4544,"lat":46.0514},"weather":{"id":804,"main":"Clouds","description":"overcast clouds","icon":"04n"},"temperature":4.36,"feels_like":2.64,"temp_min":1.43,"temp_max":5.7,"pressure":1008,"humidity":49,"wind":{"speed":1.98,"deg":67,"gust":1.79},"rain":{},"clouds":100,"sunrise":1733553769,"sunset":1733585343,"timestamp":1733593413}
{"_id":{"$oid":"67548a7edc15aebe5bc3c6fd"},"city":"Trento","coordinates":{"lon":11.1211,"lat":46.0679},"weather":{"id":801,"main":"Clouds","description":"few clouds","icon":"02n"},"temperature":4.37,"feels_like":0.03,"temp_min":2.72,"temp_max":6.98,"pressure":1008,"humidity":54,"wind":{"speed":6.17,"deg":180},"rain":{},"clouds":20,"sunrise":1733553853,"sunset":1733585419,"timestamp":1733592998}
{"_id":{"$oid":"67548a7fdc15aebe5bc3c6fe"},"city":"Rovereto","coordinates":{"lon":11.0387,"lat":45.8896},"weather":{"id":804,"main":"Clouds","description":"overcast clouds","icon":"04n"},"temperature":4.88,"feels_like":2.85,"temp_min":2.93,"temp_max":7.05,"pressure":1007,"humidity":58,"wind":{"speed":2.39,"deg":57,"gust":2.92},"rain":{},"clouds":100,"sunrise":1733553833,"sunset":1733585478,"timestamp":1733593559}
{"_id":{"$oid":"67548a80dc15aebe5bc3c6ff"},"city":"Pergine Valsugana","coordinates":{"lon":11.238,"lat":46.065},"weather":{"id":801,"main":"Clouds","description":"few clouds","icon":"02n"},"temperature":2.87,"feels_like":-4.13,"temp_min":1.01,"temp_max":5.13,"pressure":1008,"humidity":51,"wind":{"speed":16.09,"deg":0,"gust":16.09},"rain":{},"clouds":20,"sunrise":1733553824,"sunset":1733585392,"timestamp":1733593666}
{"_id":{"$oid":"67548a82dc15aebe5bc3c700"},"city":"Arco","coordinates":{"lon":10.8867,"lat":45.9177},"weather":{"id":804,"main":"Clouds","description":"overcast clouds","icon":"04n"},"temperature":6.09,"feels_like":3.82,"temp_min":6.09,"temp_max":6.77,"pressure":1007,"humidity":64,"wind":{"speed":3,"deg":33,"gust":4.13},"rain":{},"clouds":100,"sunrise":1733553876,"sunset":1733585508,"timestamp":1733593407}
{"_id":{"$oid":"67548a83dc15aebe5bc3c701"},"city":"Riva del Garda","coordinates":{"lon":10.8412,"lat":45.8858},"weather":{"id":804,"main":"Clouds","description":"overcast clouds","icon":"04n"},"temperature":6.17,"feels_like":3.69,"temp_min":6.17,"temp_max":6.17,"pressure":1007,"humidity":58,"wind":{"speed":3.34,"deg":33,"gust":4.59},"rain":{},"clouds":100,"sunrise":1733553880,"sunset":1733585526,"timestamp":1733593668}
{"_id":{"$oid":"67548a84dc15aebe5bc3c702"},"city":"Lavis","coordinates":{"lon":11.1129,"lat":46.1395},"weather":{"id":801,"main":"Clouds","description":"few clouds","icon":"02n"},"temperature":4.04,"feels_like":-0.39,"temp_min":2.05,"temp_max":5.83,"pressure":1008,"humidity":52,"wind":{"speed":6.17,"deg":180},"rain":{},"clouds":20,"sunrise":1733553871,"sunset":1733585405,"timestamp":1733593409}
{"_id":{"$oid":"67548a85dc15aebe5bc3c703"},"city":"Aalen","coordinates":{"lon":10.0933,"lat":48.8378},"weather":{"id":804,"main":"Clouds","description":"overcast clouds","icon":"04n"},"temperature":4.97,"feels_like":1.49,"temp_min":4.03,"temp_max":5.98,"pressure":1003,"humidity":92,"wind":{"speed":4.61,"deg":237,"gust":10.61},"rain":{},"clouds":100,"sunrise":1733554755,"sunset":1733585011,"timestamp":1733593584}
{"_id":{"$oid":"67548a86dc15aebe5bc3c704"},"city":"Mori","coordinates":{"lon":137.9333,"lat":34.8333},"weather":{"id":500,"main":"Rain","description":"light rain","icon":"10n"},"temperature":8.02,"feels_like":5.12,"temp_min":8.02,"temp_max":8.02,"pressure":1014,"humidity":54,"wind":{"speed":4.98,"deg":292,"gust":12.78},"rain":{"1h":0.11},"clouds":100,"sunrise":1733607809,"sunset":1733643426,"timestamp":1733593411}
{"_id":{"$oid":"67548a87dc15aebe5bc3c705"},"city":"Mezzolombardo","coordinates":{"lon":11.0968,"lat":46.209},"weather":{"id":801,"main":"Clouds","description":"few clouds","icon":"02n"},"temperature":4.35,"feels_like":0,"temp_min":2.1,"temp_max":5.89,"pressure":1008,"humidity":49,"wind":{"speed":6.17,"deg":180},"rain":{},"clouds":20,"sunrise":1733553890,"sunset":1733585393,"timestamp":1733593672}
{"_id":{"$oid":"67548a88dc15aebe5bc3c706"},"city":"Borgo Valsugana","coordinates":{"lon":11.4544,"lat":46.0514},"weather":{"id":804,"main":"Clouds","description":"overcast clouds","icon":"04n"},"temperature":4.36,"feels_like":2.64,"temp_min":1.43,"temp_max":5.7,"pressure":1008,"humidity":49,"wind":{"speed":1.98,"deg":67,"gust":1.79},"rain":{},"clouds":100,"sunrise":1733553769,"sunset":1733585343,"timestamp":1733593413}
{"_id":{"$oid":"6755dc09dc15aebe5bc3c707"},"city":"Trento","coordinates":{"lon":11.1211,"lat":46.0679},"weather":{"id":741,"main":"Fog","description":"fog","icon":"50n"},"temperature":5.16,"feels_like":-0.27,"temp_min":3.84,"temp_max":6.77,"pressure":1004,"humidity":81,"wind":{"speed":10.29,"deg":10},"rain":{},"clouds":100,"sunrise":1733640312,"sunset":1733671811,"timestamp":1733680137}
{"_id":{"$oid":"6755dc0adc15aebe5bc3c708"},"city":"Rovereto","coordinates":{"lon":11.0387,"lat":45.8896},"weather":{"id":500,"main":"Rain","description":"light rain","icon":"10n"},"temperature":5.38,"feels_like":4.6,"temp_min":3.92,"temp_max":6.55,"pressure":1003,"humidity":90,"wind":{"speed":1.34,"deg":60,"gust":1.42},"rain":{"1h":0.32},"clouds":100,"sunrise":1733640293,"sunset":1733671870,"timestamp":1733680138}
{"_id":{"$oid":"6755dc0bdc15aebe5bc3c709"},"city":"Pergine Valsugana","coordinates":{"lon":11.238,"lat":46.065},"weather":{"id":741,"main":"Fog","description":"fog","icon":"50n"},"temperature":3.84,"feels_like":-2.03,"temp_min":2,"temp_max":4.93,"pressure":1003,"humidity":77,"wind":{"speed":10.29,"deg":10},"rain":{},"clouds":100,"sunrise":1733640284,"sunset":1733671784,"timestamp":1733680139}
{"_id":{"$oid":"6755dc0cdc15aebe5bc3c70a"},"city":"Arco","coordinates":{"lon":10.8867,"lat":45.9177},"weather":{"id":500,"main":"Rain","description":"light rain","icon":"10n"},"temperature":5.65,"feels_like":4.82,"temp_min":4.77,"temp_max":7.16,"pressure":1003,"humidity":94,"wind":{"speed":1.4,"deg":32,"gust":1.64},"rain":{"1h":0.12},"clouds":100,"sunrise":1733640335,"sunset":1733671901,"timestamp":1733680140}
{"_id":{"$oid":"6755dc0ddc15aebe5bc3c70b"},"city":"Riva del Garda","coordinates":{"lon":10.8412,"lat":45.8858},"weather":{"id":804,"main":"Clouds","description":"overcast clouds","icon":"04n"},"temperature":6.89,"feels_like":5.94,"temp_min":6.72,"temp_max":8.37,"pressure":1003,"humidity":84,"wind":{"speed":1.64,"deg":33,"gust":1.93},"rain":{},"clouds":100,"sunrise":1733640339,"sunset":1733671919,"timestamp":1733679900}
{"_id":{"$oid":"6755dc0edc15aebe5bc3c70c"},"city":"Lavis","coordinates":{"lon":11.1129,"lat":46.1395},"weather":{"id":600,"main":"Snow","description":"light snow","icon":"13n"},"temperature":5.23,"feels_like":-0.18,"temp_min":3.83,"temp_max":6.14,"pressure":1004,"humidity":79,"wind":{"speed":10.29,"deg":10},"rain":{},"clouds":100,"sunrise":1733640330,"sunset":1733671797,"timestamp":1733679901}
{"_id":{"$oid":"6755dc0fdc15aebe5bc3c70d"},"city":"Aalen","coordinates":{"lon":10.0933,"lat":48.8378},"weather":{"id":501,"main":"Rain","description":"moderate rain","icon":"10n"},"temperature":3.58,"feels_like":0.53,"temp_min":2.37,"temp_max":3.93,"pressure":1010,"humidity":94,"wind":{"speed":3.37,"deg":45,"gust":8.6},"rain":{"1h":3.65},"clouds":100,"sunrise":1733641218,"sunset":1733671399,"timestamp":1733679886}
{"_id":{"$oid":"6755dc10dc15aebe5bc3c70e"},"city":"Mori","coordinates":{"lon":137.9333,"lat":34.8333},"weather":{"id":800,"main":"Clear","description":"clear sky","icon":"01n"},"temperature":4.69,"feels_like":2.69,"temp_min":4.69,"temp_max":4.69,"pressure":1017,"humidity":54,"wind":{"speed":2.32,"deg":339,"gust":4.85},"rain":{},"clouds":6,"sunrise":1733694256,"sunset":1733729832,"timestamp":1733680144}
{"_id":{"$oid":"6755dc11dc15aebe5bc3c70f"},"city":"Mezzolombardo","coordinates":{"lon":11.0968,"lat":46.209},"weather":{"id":600,"main":"Snow","description":"light snow","icon":"13n"},"temperature":5.31,"feels_like":-0.08,"temp_min":3.89,"temp_max":6.58,"pressure":1004,"humidity":78,"wind":{"speed":10.29,"deg":10},"rain":{},"clouds":100,"sunrise":1733640350,"sunset":1733671785,"timestamp":1733680145}
{"_id":{"$oid":"6755dc12dc15aebe5bc3c710"},"city":"Borgo Valsugana","coordinates":{"lon":11.4544,"lat":46.0514},"weather":{"id":500,"main":"Rain","description":"light rain","icon":"10n"},"temperature":4.41,"feels_like":4.41,"temp_min":2.55,"temp_max":5.47,"pressure":1003,"humidity":81,"wind":{"speed":1.24,"deg":17,"gust":1.8},"rain":{"1h":0.28},"clouds":100,"sunrise":1733640229,"sunset":1733671735,"timestamp":1733680146}
{"_id":{"$oid":"67572d94dc15aebe5bc3c711"},"city":"Trento","coordinates":{"lon":11.1211,"lat":46.0679},"weather":{"id":802,"main":"Clouds","description":"scattered clouds","icon":"03n"},"temperature":5.57,"feels_like":1.18,"temp_min":4.08,"temp_max":6.77,"pressure":1014,"humidity":81,"wind":{"speed":7.2,"deg":350},"rain":{},"clouds":40,"sunrise":1733726770,"sunset":1733758206,"timestamp":1733766548}
{"_id":{"$oid":"67572d95dc15aebe5bc3c712"},"city":"Rovereto","coordinates":{"lon":11.0387,"lat":45.8896},"weather":{"id":804,"main":"Clouds","description":"overcast clouds","icon":"04n"},"temperature":5.6,"feels_like":5.6,"temp_min":4.11,"temp_max":6.49,"pressure":1014,"humidity":91,"wind":{"speed":0.68,"deg":82,"gust":0.91},"rain":{},"clouds":91,"sunrise":1733726750,"sunset":1733758265,"timestamp":1733766527}
{"_id":{"$oid":"67572d96dc15aebe5bc3c713"},"city":"Pergine Valsugana","coordinates":{"lon":11.238,"lat":46.065},"weather":{"id":802,"main":"Clouds","description":"scattered clouds","icon":"03n"},"temperature":4.17,"feels_like":-0.63,"temp_min":2.2,"temp_max":4.93,"pressure":1014,"humidity":77,"wind":{"speed":7.2,"deg":350},"rain":{},"clouds":40,"sunrise":1733726741,"sunset":1733758178,"timestamp":1733766300}
{"_id":{"$oid":"67572d97dc15aebe5bc3c714"},"city":"Arco","coordinates":{"lon":10.8867,"lat":45.9177},"weather":{"id":804,"main":"Clouds","description":"overcast clouds","icon":"04n"},"temperature":6.25,"feels_like":6.25,"temp_min":4.77,"temp_max":6.64,"pressure":1014,"humidity":93,"wind":{"speed":0.98,"deg":76,"gust":0.7},"rain":{},"clouds":89,"sunrise":1733726793,"sunset":1733758296,"timestamp":1733766409}
{"_id":{"$oid":"67572d98dc15aebe5bc3c715"},"city":"Riva del Garda","coordinates":{"lon":10.8412,"lat":45.8858},"weather":{"id":804,"main":"Clouds","description":"overcast clouds","icon":"04n"},"temperature":6.89,"feels_like":6.89,"temp_min":6.01,"temp_max":8.92,"pressure":1014,"humidity":89,"wind":{"speed":1.14,"deg":72,"gust":0.76},"rain":{},"clouds":90,"sunrise":1733726797,"sunset":1733758314,"timestamp":1733766552}
{"_id":{"$oid":"67572d99dc15aebe5bc3c716"},"city":"Lavis","coordinates":{"lon":11.1129,"lat":46.1395},"weather":{"id":802,"main":"Clouds","description":"scattered clouds","icon":"03n"},"temperature":5.42,"feels_like":0.98,"temp_min":3.83,"temp_max":6.52,"pressure":1014,"humidity":80,"wind":{"speed":7.2,"deg":350},"rain":{},"clouds":40,"sunrise":1733726788,"sunset":1733758192,"timestamp":1733766553}
{"_id":{"$oid":"67572d9adc15aebe5bc3c717"},"city":"Aalen","coordinates":{"lon":10.0933,"lat":48.8378},"weather":{"id":600,"main":"Snow","description":"light snow","icon":"13n"},"temperature":1.26,"feels_like":-3.09,"temp_min":0.7,"temp_max":1.66,"pressure":1021,"humidity":91,"wind":{"speed":4.57,"deg":62,"gust":9.27},"rain":{},"clouds":99,"sunrise":1733727680,"sunset":1733757789,"timestamp":1733766398}
{"_id":{"$oid":"67572d9bdc15aebe5bc3c718"},"city":"Mori","coordinates":{"lon":137.9333,"lat":34.8333},"weather":{"id":804,"main":"Clouds","description":"overcast clouds","icon":"04n"},"temperature":4.69,"feels_like":2.97,"temp_min":4.69,"temp_max":4.69,"pressure":1018,"humidity":63,"wind":{"speed":2.04,"deg":328,"gust":4.83},"rain":{},"clouds":93,"sunrise":1733780701,"sunset":1733816239,"timestamp":1733766555}
{"_id":{"$oid":"67572d9cdc15aebe5bc3c719"},"city":"Mezzolombardo","coordinates":{"lon":11.0968,"lat":46.209},"weather":{"id":802,"main":"Clouds","description":"scattered clouds","icon":"03n"},"temperature":5.38,"feels_like":0.93,"temp_min":3.89,"temp_max":6.58,"pressure":1014,"humidity":79,"wind":{"speed":7.2,"deg":350},"rain":{},"clouds":40,"sunrise":1733726808,"sunset":1733758180,"timestamp":1733766556}
{"_id":{"$oid":"67572d9ddc15aebe5bc3c71a"},"city":"Borgo Valsugana","coordinates":{"lon":11.4544,"lat":46.0514},"weather":{"id":804,"main":"Clouds","description":"overcast clouds","icon":"04n"},"temperature":4.8,"feels_like":4.8,"temp_min":4.09,"temp_max":5.47,"pressure":1014,"humidity":81,"wind":{"speed":0.79,"deg":87,"gust":0.93},"rain":{},"clouds":99,"sunrise":1733726686,"sunset":1733758129,"timestamp":1733766557}
{"_id":{"$oid":"67587f1fdc15aebe5bc3c71b"},"city":"Trento","coordinates":{"lon":11.1211,"lat":46.0679},"weather":{"id":802,"main":"Clouds","description":"scattered clouds","icon":"03n"},"temperature":6.37,"feels_like":3.48,"temp_min":5.08,"temp_max":7.32,"pressure":1022,"humidity":74,"wind":{"speed":4.12,"deg":20},"rain":{},"clouds":40,"sunrise":1733813226,"sunset":1733844603,"timestamp":1733852924}
{"_id":{"$oid":"67587f20dc15aebe5bc3c71c"},"city":"Rovereto","coordinates":{"lon":11.0387,"lat":45.8896},"weather":{"id":804,"main":"Clouds","description":"overcast clouds","icon":"04n"},"temperature":6.52,"feels_like":6.52,"temp_min":4.59,"temp_max":7.66,"pressure":1022,"humidity":87,"wind":{"speed":0.45,"deg":110,"gust":0.34},"rain":{},"clouds":100,"sunrise":1733813205,"sunset":1733844663,"timestamp":1733852960}
{"_id":{"$oid":"67587f21dc15aebe5bc3c71d"},"city":"Pergine Valsugana","coordinates":{"lon":11.238,"lat":46.065},"weather":{"id":802,"main":"Clouds","description":"scattered clouds","icon":"03n"},"temperature":4.14,"feels_like":0.73,"temp_min":2.68,"temp_max":5.48,"pressure":1022,"humidity":75,"wind":{"speed":4.12,"deg":20},"rain":{},"clouds":40,"sunrise":1733813197,"sunset":1733844576,"timestamp":1733852961}
{"_id":{"$oid":"67587f22dc15aebe5bc3c71e"},"city":"Arco","coordinates":{"lon":10.8867,"lat":45.9177},"weather":{"id":804,"main":"Clouds","description":"overcast clouds","icon":"04n"},"temperature":7.11,"feels_like":7.11,"temp_min":5.77,"temp_max":8.27,"pressure":1021,"humidity":86,"wind":{"speed":0.54,"deg":53,"gust":0.37},"rain":{},"clouds":100,"sunrise":1733813248,"sunset":1733844693,"timestamp":1733852962}
{"_id":{"$oid":"67587f23dc15aebe5bc3c71f"},"city":"Riva del Garda","coordinates":{"lon":10.8412,"lat":45.8858},"weather":{"id":804,"main":"Clouds","description":"overcast clouds","icon":"04n"},"temperature":7.27,"feels_like":7.27,"temp_min":7.12,"temp_max":8.35,"pressure":1021,"humidity":82,"wind":{"speed":0.71,"deg":53,"gust":0.48},"rain":{},"clouds":100,"sunrise":1733813252,"sunset":1733844711,"timestamp":1733852709}
{"_id":{"$oid":"67587f24dc15aebe5bc3c720"},"city":"Lavis","coordinates":{"lon":11.1129,"lat":46.1395},"weather":{"id":802,"main":"Clouds","description":"scattered clouds","icon":"03n"},"temperature":6.17,"feels_like":3.23,"temp_min":4.83,"temp_max":7.07,"pressure":1021,"humidity":71,"wind":{"speed":4.12,"deg":20},"rain":{},"clouds":40,"sunrise":1733813244,"sunset":1733844589,"timestamp":1733852964}
{"_id":{"$oid":"67587f25dc15aebe5bc3c721"},"city":"Aalen","coordinates":{"lon":10.0933,"lat":48.8378},"weather":{"id":804,"main":"Clouds","description":"overcast clouds","icon":"04n"},"temperature":2.03,"feels_like":-1.38,"temp_min":1.26,"temp_max":3.43,"pressure":1026,"humidity":92,"wind":{"speed":3.41,"deg":61,"gust":7.55},"rain":{},"clouds":100,"sunrise":1733814139,"sunset":1733844183,"timestamp":1733852930}
{"_id":{"$oid":"67587f26dc15aebe5bc3c722"},"city":"Mori","coordinates":{"lon":137.9333,"lat":34.8333},"weather":{"id":803,"main":"Clouds","description":"broken clouds","icon":"04n"},"temperature":6.91,"feels_like":5,"temp_min":6.91,"temp_max":6.91,"pressure":1016,"humidity":69,"wind":{"speed":2.71,"deg":301,"gust":8.25},"rain":{},"clouds":83,"sunrise":1733867145,"sunset":1733902649,"timestamp":1733852966}
{"_id":{"$oid":"67587f27dc15aebe5bc3c723"},"city":"Mezzolombardo","coordinates":{"lon":11.0968,"lat":46.209},"weather":{"id":802,"main":"Clouds","description":"scattered clouds","icon":"03n"},"temperature":6.13,"feels_like":3.18,"temp_min":4.89,"temp_max":7.13,"pressure":1021,"humidity":70,"wind":{"speed":4.12,"deg":20},"rain":{},"clouds":40,"sunrise":1733813264,"sunset":1733844577,"timestamp":1733852820}
{"_id":{"$oid":"67587f29dc15aebe5bc3c724"},"city":"Borgo Valsugana","coordinates":{"lon":11.4544,"lat":46.0514},"weather":{"id":804,"main":"Clouds","description":"overcast clouds","icon":"04n"},"temperature":5.25,"feels_like":4.35,"temp_min":4.65,"temp_max":6.02,"pressure":1023,"humidity":81,"wind":{"speed":1.41,"deg":49,"gust":1.29},"rain":{},"clouds":94,"sunrise":1733813142,"sunset":1733844527,"timestamp":1733852969}
{"_id":{"$oid":"6759d0aadc15aebe5bc3c725"},"city":"Trento","coordinates":{"lon":11.1211,"lat":46.0679},"weather":{"id":800,"main":"Clear","description":"clear sky","icon":"01n"},"temperature":6.41,"feels_like":6.41,"temp_min":3.07,"temp_max":8.17,"pressure":1026,"humidity":65,"wind":{"speed":1.03,"deg":0},"rain":{},"clouds":0,"sunrise":1733899679,"sunset":1733931003,"timestamp":1733939262}
{"_id":{"$oid":"6759d0abdc15aebe5bc3c726"},"city":"Rovereto","coordinates":{"lon":11.0387,"lat":45.8896},"weather":{"id":803,"main":"Clouds","description":"broken clouds","icon":"04n"},"temperature":7.06,"feels_like":7.06,"temp_min":3.14,"temp_max":8.24,"pressure":1026,"humidity":75,"wind":{"speed":0.89,"deg":47,"gust":1.79},"rain":{},"clouds":80,"sunrise":1733899659,"sunset":1733931063,"timestamp":1733939371}
{"_id":{"$oid":"6759d0acdc15aebe5bc3c727"},"city":"Pergine Valsugana","coordinates":{"lon":11.238,"lat":46.065},"weather":{"id":800,"main":"Clear","description":"clear sky","icon":"01n"},"temperature":4.62,"feels_like":4.62,"temp_min":1.77,"temp_max":6.33,"pressure":1026,"humidity":61,"wind":{"speed":1.03,"deg":0},"rain":{},"clouds":0,"sunrise":1733899651,"sunset":1733930976,"timestamp":1733939083}
{"_id":{"$oid":"6759d0addc15aebe5bc3c728"},"city":"Arco","coordinates":{"lon":10.8867,"lat":45.9177},"weather":{"id":803,"main":"Clouds","description":"broken clouds","icon":"04n"},"temperature":8.22,"feels_like":8.22,"temp_min":8.15,"temp_max":8.77,"pressure":1026,"humidity":69,"wind":{"speed":0.85,"deg":28,"gust":0.73},"rain":{},"clouds":83,"sunrise":1733899702,"sunset":1733931093,"timestamp":1733939086}
{"_id":{"$oid":"6759d0aedc15aebe5bc3c729"},"city":"Riva del Garda","coordinates":{"lon":10.8412,"lat":45.8858},"weather":{"id":804,"main":"Clouds","description":"overcast clouds","icon":"04n"},"temperature":8.37,"feels_like":8.37,"temp_min":8.23,"temp_max":8.37,"pressure":1026,"humidity":78,"wind":{"speed":1.02,"deg":26,"gust":0.82},"rain":{},"clouds":85,"sunrise":1733899705,"sunset":1733931112,"timestamp":1733939374}
{"_id":{"$oid":"6759d0afdc15aebe5bc3c72a"},"city":"Lavis","coordinates":{"lon":11.1129,"lat":46.1395},"weather":{"id":800,"main":"Clear","description":"clear sky","icon":"01n"},"temperature":5.09,"feels_like":5.09,"temp_min":2.81,"temp_max":7.92,"pressure":1026,"humidity":62,"wind":{"speed":1.03,"deg":0},"rain":{},"clouds":0,"sunrise":1733899698,"sunset":1733930989,"timestamp":1733939375}
{"_id":{"$oid":"6759d0b0dc15aebe5bc3c72b"},"city":"Aalen","coordinates":{"lon":10.0933,"lat":48.8378},"weather":{"id":804,"main":"Clouds","description":"overcast clouds","icon":"04n"},"temperature":1.91,"feels_like":1.91,"temp_min":0.31,"temp_max":3.14,"pressure":1030,"humidity":94,"wind":{"speed":1.21,"deg":73,"gust":2.26},"rain":{},"clouds":100,"sunrise":1733900596,"sunset":1733930580,"timestamp":1733939311}
{"_id":{"$oid":"6759d0b1dc15aebe5bc3c72c"},"city":"Mori","coordinates":{"lon":137.9333,"lat":34.8333},"weather":{"id":803,"main":"Clouds","description":"broken clouds","icon":"04n"},"temperature":6.36,"feels_like":5.08,"temp_min":6.36,"temp_max":6.36,"pressure":1014,"humidity":58,"wind":{"speed":1.87,"deg":335,"gust":4.52},"rain":{},"clouds":58,"sunrise":1733953588,"sunset":1733989060,"timestamp":1733939377}
{"_id":{"$oid":"6759d0b2dc15aebe5bc3c72d"},"city":"Mezzolombardo","coordinates":{"lon":11.0968,"lat":46.209},"weather":{"id":800,"main":"Clear","description":"clear sky","icon":"01n"},"temperature":5.13,"feels_like":5.13,"temp_min":2.87,"temp_max":7.97,"pressure":1026,"humidity":60,"wind":{"speed":1.03,"deg":0},"rain":{},"clouds":0,"sunrise":1733899717,"sunset":1733930977,"timestamp":1733939378}
{"_id":{"$oid":"6759d0b3dc15aebe5bc3c72e"},"city":"Borgo Valsugana","coordinates":{"lon":11.4544,"lat":46.0514},"weather":{"id":803,"main":"Clouds","description":"broken clouds","icon":"04n"},"temperature":6.11,"feels_like":6.11,"temp_min":1.77,"temp_max":6.87,"pressure":1026,"humidity":64,"wind":{"speed":0.79,"deg":5,"gust":0.79},"rain":{},"clouds":59,"sunrise":1733899596,"sunset":1733930927,"timestamp":1733939337}
{"_id":{"$oid":"675b2234dc15aebe5bc3c72f"},"city":"Trento","coordinates":{"lon":11.1211,"lat":46.0679},"weather":{"id":800,"main":"Clear","description":"clear sky","icon":"01n"},"temperature":2.15,"feels_like":2.15,"temp_min":1.19,"temp_max":6.5,"pressure":1030,"humidity":73,"wind":{"speed":0.73,"deg":75,"gust":0.95},"rain":{},"clouds":1,"sunrise":1733986131,"sunset":1734017406,"timestamp":1734025780}
{"_id":{"$oid":"675b2235dc15aebe5bc3c730"},"city":"Rovereto","coordinates":{"lon":11.0387,"lat":45.8896},"weather":{"id":800,"main":"Clear","description":"clear sky","icon":"01n"},"temperature":4.94,"feels_like":4.94,"temp_min":1.26,"temp_max":6.57,"pressure":1030,"humidity":75,"wind":{"speed":0.45,"deg":56,"gust":0.89},"rain":{},"clouds":1,"sunrise":1733986110,"sunset":1734017466,"timestamp":1734025728}
{"_id":{"$oid":"675b2237dc15aebe5bc3c731"},"city":"Pergine Valsugana","coordinates":{"lon":11.238,"lat":46.065},"weather":{"id":800,"main":"Clear","description":"clear sky","icon":"01n"},"temperature":0.31,"feels_like":-1.14,"temp_min":-0.66,"temp_max":4.66,"pressure":1030,"humidity":72,"wind":{"speed":1.34,"deg":7,"gust":1.34},"rain":{},"clouds":2,"sunrise":1733986102,"sunset":1734017379,"timestamp":1734025783}
{"_id":{"$oid":"675b2238dc15aebe5bc3c732"},"city":"Arco","coordinates":{"lon":10.8867,"lat":45.9177},"weather":{"id":800,"main":"Clear","description":"clear sky","icon":"01n"},"temperature":7.18,"feels_like":7.18,"temp_min":7.18,"temp_max":9.77,"pressure":1030,"humidity":82,"wind":{"speed":1.15,"deg":27,"gust":1.11},"rain":{},"clouds":1,"sunrise":1733986153,"sunset":1734017496,"timestamp":1734025784}
{"_id":{"$oid":"675b2239dc15aebe5bc3c733"},"city":"Riva del Garda","coordinates":{"lon":10.8412,"lat":45.8858},"weather":{"id":800,"main":"Clear","description":"clear sky","icon":"01n"},"temperature":3.39,"feels_like":2.27,"temp_min":3.39,"temp_max":7.26,"pressure":1030,"humidity":80,"wind":{"speed":1.39,"deg":27,"gust":1.32},"rain":{},"clouds":0,"sunrise":1733986157,"sunset":1734017514,"timestamp":1734025785}
{"_id":{"$oid":"675b223adc15aebe5bc3c734"},"city":"Lavis","coordinates":{"lon":11.1129,"lat":46.1395},"weather":{"id":800,"main":"Clear","description":"clear sky","icon":"01n"},"temperature":2.18,"feels_like":2.18,"temp_min":0.93,"temp_max":6.25,"pressure":1030,"humidity":67,"wind":{"speed":0.35,"deg":47,"gust":0.91},"rain":{},"clouds":1,"sunrise":1733986149,"sunset":1734017392,"timestamp":1734025786}
{"_id":{"$oid":"675b223bdc15aebe5bc3c735"},"city":"Aalen","coordinates":{"lon":10.0933,"lat":48.8378},"weather":{"id":802,"main":"Clouds","description":"scattered clouds","icon":"03n"},"temperature":0.58,"feels_like":-1.27,"temp_min":-0.41,"temp_max":1.77,"pressure":1030,"humidity":94,"wind":{"speed":1.62,"deg":107,"gust":2.48},"rain":{},"clouds":30,"sunrise":1733987051,"sunset":1734016979,"timestamp":1734025787}
{"_id":{"$oid":"675b223cdc15aebe5bc3c736"},"city":"Mori","coordinates":{"lon":137.9333,"lat":34.8333},"weather":{"id":802,"main":"Clouds","description":"scattered clouds","icon":"03n"},"temperature":2.47,"feels_like":0.34,"temp_min":2.47,"temp_max":2.47,"pressure":1020,"humidity":59,"wind":{"speed":2.07,"deg":319,"gust":5.24},"rain":{},"clouds":29,"sunrise":1734040030,"sunset":1734075473,"timestamp":1734025788}
{"_id":{"$oid":"675b223ddc15aebe5bc3c737"},"city":"Mezzolombardo","coordinates":{"lon":11.0968,"lat":46.209},"weather":{"id":800,"main":"Clear","description":"clear sky","icon":"01n"},"temperature":2.34,"feels_like":2.34,"temp_min":0.99,"temp_max":3.8,"pressure":1030,"humidity":65,"wind":{"speed":0.58,"deg":321,"gust":0.94},"rain":{},"clouds":1,"sunrise":1733986169,"sunset":1734017379,"timestamp":1734025789}
{"_id":{"$oid":"675b223edc15aebe5bc3c738"},"city":"Borgo Valsugana","coordinates":{"lon":11.4544,"lat":46.0514},"weather":{"id":800,"main":"Clear","description":"clear sky","icon":"01n"},"temperature":0.75,"feels_like":0.75,"temp_min":-0.11,"temp_max":2.69,"pressure":1030,"humidity":73,"wind":{"speed":1.24,"deg":53,"gust":1.12},"rain":{},"clouds":2,"sunrise":1733986047,"sunset":1734017330,"timestamp":1734025790}
